Workbook

Sheet Dashboard
B2: City on a Hill | Growth Partner Dashboard
B3: Live view of every prospect screened. Updates as the Backend is filled in.
B5: Prospects screened | D5: Qualified | F5: Qualification rate | H5: Christian-led | J5: Avg intent (out of 10)
B6: =COUNTA(Backend!$A$22:$A$221) -> 5 | D6: =COUNTIF(Backend!$AC$22:$AC$221,"Qualified*") -> 3 | F6: =IFERROR(COUNTIF(Backend!$AC$22:$AC$221,"Qualified*")/COUNTA(Backend!$A$22:$A$221),0) -> 0.6 | H6: =IFERROR(COUNTIF(Backend!$V$22:$V$221,"Yes")/COUNTA(Backend!$A$22:$A$221),0) -> 0.8 | J6: =IFERROR(AVERAGE(Backend!$AB$22:$AB$221),0) -> 7
B8: Outcomes
B9: Outcome | D9: Prospects | E9: Share
B10: Qualified: high intent | D10: =COUNTIF(Backend!$AC$22:$AC$221,B10) -> 2 | E10: =IFERROR(D10/SUM($D$10:$D$13),0) -> 0.4
B11: Qualified: nurture | D11: =COUNTIF(Backend!$AC$22:$AC$221,B11) -> 1 | E11: =IFERROR(D11/SUM($D$10:$D$13),0) -> 0.2
B12: Development pathway | D12: =COUNTIF(Backend!$AC$22:$AC$221,B12) -> 1 | E12: =IFERROR(D12/SUM($D$10:$D$13),0) -> 0.2
B13: Not a fit | D13: =COUNTIF(Backend!$AC$22:$AC$221,B13) -> 1 | E13: =IFERROR(D13/SUM($D$10:$D$13),0) -> 0.2
B15: Where prospects fall out
B16: Reason | D16: Prospects | E16: Share
B17: A. Not a real business | D17: =COUNTIF(Backend!$Y$22:$Y$221,"Fail") -> 1 | E17: =IFERROR(D17/COUNTA(Backend!$A$22:$A$221),0) -> 0.2
B18: B. Turnover not met | D18: =COUNTIF(Backend!$Z$22:$Z$221,"Fail") -> 1 | E18: =IFERROR(D18/COUNTA(Backend!$A$22:$A$221),0) -> 0.2
B19: C. No leadership team | D19: =COUNTIF(Backend!$AA$22:$AA$221,"Fail") -> 2 | E19: =IFERROR(D19/COUNTA(Backend!$A$22:$A$221),0) -> 0.4
B20: E1. Not Christian-led | D20: =COUNTIF(Backend!$V$22:$V$221,"No") -> 1 | E20: =IFERROR(D20/COUNTA(Backend!$A$22:$A$221),0) -> 0.2
B21: Cross-check concern | D21: =COUNTIF(Backend!$X$22:$X$221,"Yes") -> 1 | E21: =IFERROR(D21/COUNTA(Backend!$A$22:$A$221),0) -> 0.2
B22: A prospect can fall out for more than one reason, so shares can total more than 100%.
B24: Turnover bands | G24: Kingdom connection (E2)
B25: Band | D25: Prospects | E25: Share | G25: Answer | J25: Prospects | K25: Share
B26: Under £50k | D26: =COUNTIF(Backend!$J$22:$J$221,B26) -> 1 | E26: =IFERROR(D26/COUNTA(Backend!$A$22:$A$221),0) -> 0.2 | G26: 2: Already adds value, with example | J26: =COUNTIF(Backend!$W$22:$W$221,2) -> 2 | K26: =IFERROR(J26/SUM($J$26:$J$28),0) -> 0.4
B27: £50k to £250k | D27: =COUNTIF(Backend!$J$22:$J$221,B27) -> 1 | E27: =IFERROR(D27/COUNTA(Backend!$A$22:$A$221),0) -> 0.2 | G27: 1: Willing, no example yet | J27: =COUNTIF(Backend!$W$22:$W$221,1) -> 2 | K27: =IFERROR(J27/SUM($J$26:$J$28),0) -> 0.4
B28: £250k to £1m | D28: =COUNTIF(Backend!$J$22:$J$221,B28) -> 2 | E28: =IFERROR(D28/COUNTA(Backend!$A$22:$A$221),0) -> 0.4 | G28: 0: Not a priority | J28: =COUNTIF(Backend!$W$22:$W$221,0) -> 1 | K28: =IFERROR(J28/SUM($J$26:$J$28),0) -> 0.2
B29: £1m to £5m | D29: =COUNTIF(Backend!$J$22:$J$221,B29) -> 1 | E29: =IFERROR(D29/COUNTA(Backend!$A$22:$A$221),0) -> 0.2 | G29: Shown for insight. Does not change the outcome.
B30: Over £5m | D30: =COUNTIF(Backend!$J$22:$J$221,B30) -> 0 | E30: =IFERROR(D30/COUNTA(Backend!$A$22:$A$221),0) -> 0

Sheet Backend
A1: Backend: prospect responses
A2: Enter one prospect per row from row 22. Yellow columns are inputs. Grey columns calculate themselves. Rows marked Sample are for illustration: delete them before real use.
A4: Outcome | B4: Prospects
A5: Qualified: high intent | B5: =COUNTIF($AC$22:$AC$221,A5) -> 2
A6: Qualified: nurture | B6: =COUNTIF($AC$22:$AC$221,A6) -> 1
A7: Development pathway | B7: =COUNTIF($AC$22:$AC$221,A7) -> 1
A8: Not a fit | B8: =COUNTIF($AC$22:$AC$221,A8) -> 1
A9: Total | B9: =SUM(B5:B8) -> 5
A20: Prospect | F20: A. Real business | J20: B. Turnover | M20: C. Leadership | Q20: D. Intent to grow (0 to 2) | V20: E. Kingdom | X20: Check | Y20: Calculated
A21: Business name | B21: Contact | C21: Role | D21: Date of call | E21: Reviewer | F21: A1 Registered and owner named | G21: A2 Trading and customers | H21: A3 Recent paying customers | I21: A4 Public presence | J21: B1 Turnover band | K21: B2 Knows revenue split | L21: B3 Accounts and filings current | M21: C1 Other decision maker | N21: C2 Runs without founder | O21: C3 Sales, delivery, finance owned | P21: C4 Leadership rhythm | Q21: D1 12-month target | R21: D2 Invested in growth | S21: D3 Knows constraint | T21: D4 Cost of standing still | U21: D5 Start date and decision maker | V21: E1 Christian-led | W21: E2 Adds value to Christian businesses | X21: Cross-check concern | Y21: Gate A | Z21: Gate B | AA21: Gate C | AB21: Intent score /10 | AC21: Outcome | AD21: Notes
A22: Sample: Grace Joinery Ltd | E22: Sample | F22: Yes | G22: Yes | H22: Yes | I22: Yes | J22: £250k to £1m | K22: Yes | L22: Yes | M22: Yes | N22: Yes | O22: Yes | P22: Yes | Q22: 2 | R22: 2 | S22: 2 | T22: 1 | U22: 2 | V22: Yes | W22: 2 | X22: No | Y22: =IF($A22="","",IF(COUNTIF(F22:I22,"Yes")=4,"Pass","Fail")) -> Pass | Z22: =IF($A22="","",IF(AND(IFERROR(MATCH(J22,Settings!$A$10:$A$14,0),0)>=MATCH(Settings!$B$4,Settings!$A$10:$A$14,0),K22="Yes",L22="Yes"),"Pass","Fail")) -> Pass | AA22: =IF($A22="","",IF(COUNTIF(M22:P22,"Yes")=4,"Pass","Fail")) -> Pass | AB22: =IF($A22="","",SUM(Q22:U22)) -> 9 | AC22: =IF($A22="","",IF(OR(Y22="Fail",X22="Yes",V22<>"Yes"),"Not a fit",IF(OR(Z22="Fail",AA22="Fail"),"Development pathway",IF(AB22>=Settings!$B$5,"Qualified: high intent",IF(AB22>=Settings!$B$6,"Qualified: nurture","Development pathway"))))) -> Qualified: high intent
A23: Sample: Beacon Care Services | E23: Sample | F23: Yes | G23: Yes | H23: Yes | I23: Yes | J23: £1m to £5m | K23: Yes | L23: Yes | M23: Yes | N23: Yes | O23: Yes | P23: Yes | Q23: 2 | R23: 1 | S23: 1 | T23: 1 | U23: 1 | V23: Yes | W23: 1 | X23: No | Y23: =IF($A23="","",IF(COUNTIF(F23:I23,"Yes")=4,"Pass","Fail")) -> Pass | Z23: =IF($A23="","",IF(AND(IFERROR(MATCH(J23,Settings!$A$10:$A$14,0),0)>=MATCH(Settings!$B$4,Settings!$A$10:$A$14,0),K23="Yes",L23="Yes"),"Pass","Fail")) -> Pass | AA23: =IF($A23="","",IF(COUNTIF(M23:P23,"Yes")=4,"Pass","Fail")) -> Pass | AB23: =IF($A23="","",SUM(Q23:U23)) -> 6 | AC23: =IF($A23="","",IF(OR(Y23="Fail",X23="Yes",V23<>"Yes"),"Not a fit",IF(OR(Z23="Fail",AA23="Fail"),"Development pathway",IF(AB23>=Settings!$B$5,"Qualified: high intent",IF(AB23>=Settings!$B$6,"Qualified: nurture","Development pathway"))))) -> Qualified: nurture
A24: Sample: Shepherd Digital | E24: Sample | F24: Yes | G24: Yes | H24: Yes | I24: Yes | J24: £50k to £250k | K24: Yes | L24: Yes | M24: Yes | N24: No | O24: No | P24: Yes | Q24: 2 | R24: 1 | S24: 2 | T24: 2 | U24: 2 | V24: Yes | W24: 2 | X24: No | Y24: =IF($A24="","",IF(COUNTIF(F24:I24,"Yes")=4,"Pass","Fail")) -> Pass | Z24: =IF($A24="","",IF(AND(IFERROR(MATCH(J24,Settings!$A$10:$A$14,0),0)>=MATCH(Settings!$B$4,Settings!$A$10:$A$14,0),K24="Yes",L24="Yes"),"Pass","Fail")) -> Pass | AA24: =IF($A24="","",IF(COUNTIF(M24:P24,"Yes")=4,"Pass","Fail")) -> Fail | AB24: =IF($A24="","",SUM(Q24:U24)) -> 9 | AC24: =IF($A24="","",IF(OR(Y24="Fail",X24="Yes",V24<>"Yes"),"Not a fit",IF(OR(Z24="Fail",AA24="Fail"),"Development pathway",IF(AB24>=Settings!$B$5,"Qualified: high intent",IF(AB24>=Settings!$B$6,"Qualified: nurture","Development pathway"))))) -> Development pathway
A25: Sample: Harvest Foods | E25: Sample | F25: Yes | G25: Yes | H25: Yes | I25: Yes | J25: £250k to £1m | K25: Yes | L25: Yes | M25: Yes | N25: Yes | O25: Yes | P25: Yes | Q25: 2 | R25: 2 | S25: 2 | T25: 2 | U25: 2 | V25: Yes | W25: 1 | X25: No | Y25: =IF($A25="","",IF(COUNTIF(F25:I25,"Yes")=4,"Pass","Fail")) -> Pass | Z25: =IF($A25="","",IF(AND(IFERROR(MATCH(J25,Settings!$A$10:$A$14,0),0)>=MATCH(Settings!$B$4,Settings!$A$10:$A$14,0),K25="Yes",L25="Yes"),"Pass","Fail")) -> Pass | AA25: =IF($A25="","",IF(COUNTIF(M25:P25,"Yes")=4,"Pass","Fail")) -> Pass | AB25: =IF($A25="","",SUM(Q25:U25)) -> 10 | AC25: =IF($A25="","",IF(OR(Y25="Fail",X25="Yes",V25<>"Yes"),"Not a fit",IF(OR(Z25="Fail",AA25="Fail"),"Development pathway",IF(AB25>=Settings!$B$5,"Qualified: high intent",IF(AB25>=Settings!$B$6,"Qualified: nurture","Development pathway"))))) -> Qualified: high intent
A26: Sample: Northgate Trading | E26: Sample | F26: Yes | G26: No | H26: Yes | I26: No | J26: Under £50k | K26: No | L26: No | M26: No | N26: No | O26: No | P26: No | Q26: 0 | R26: 0 | S26: 1 | T26: 0 | U26: 0 | V26: No | W26: 0 | X26: Yes | Y26: =IF($A26="","",IF(COUNTIF(F26:I26,"Yes")=4,"Pass","Fail")) -> Fail | Z26: =IF($A26="","",IF(AND(IFERROR(MATCH(J26,Settings!$A$10:$A$14,0),0)>=MATCH(Settings!$B$4,Settings!$A$10:$A$14,0),K26="Yes",L26="Yes"),"Pass","Fail")) -> Fail | AA26: =IF($A26="","",IF(COUNTIF(M26:P26,"Yes")=4,"Pass","Fail")) -> Fail | AB26: =IF($A26="","",SUM(Q26:U26)) -> 1 | AC26: =IF($A26="","",IF(OR(Y26="Fail",X26="Yes",V26<>"Yes"),"Not a fit",IF(OR(Z26="Fail",AA26="Fail"),"Development pathway",IF(AB26>=Settings!$B$5,"Qualified: high intent",IF(AB26>=Settings!$B$6,"Qualified: nurture","Development pathway"))))) -> Not a fit
Y27: =IF($A27="","",IF(COUNTIF(F27:I27,"Yes")=4,"Pass","Fail")) | Z27: =IF($A27="","",IF(AND(IFERROR(MATCH(J27,Settings!$A$10:$A$14,0),0)>=MATCH(Settings!$B$4,Settings!$A$10:$A$14,0),K27="Yes",L27="Yes"),"Pass","Fail")) | AA27: =IF($A27="","",IF(COUNTIF(M27:P27,"Yes")=4,"Pass","Fail")) | AB27: =IF($A27="","",SUM(Q27:U27)) | AC27: =IF($A27="","",IF(OR(Y27="Fail",X27="Yes",V27<>"Yes"),"Not a fit",IF(OR(Z27="Fail",AA27="Fail"),"Development pathway",IF(AB27>=Settings!$B$5,"Qualified: high intent",IF(AB27>=Settings!$B$6,"Qualified: nurture","Development pathway")))))
Y28: =IF($A28="","",IF(COUNTIF(F28:I28,"Yes")=4,"Pass","Fail")) | Z28: =IF($A28="","",IF(AND(IFERROR(MATCH(J28,Settings!$A$10:$A$14,0),0)>=MATCH(Settings!$B$4,Settings!$A$10:$A$14,0),K28="Yes",L28="Yes"),"Pass","Fail")) | AA28: =IF($A28="","",IF(COUNTIF(M28:P28,"Yes")=4,"Pass","Fail")) | AB28: =IF($A28="","",SUM(Q28:U28)) | AC28: =IF($A28="","",IF(OR(Y28="Fail",X28="Yes",V28<>"Yes"),"Not a fit",IF(OR(Z28="Fail",AA28="Fail"),"Development pathway",IF(AB28>=Settings!$B$5,"Qualified: high intent",IF(AB28>=Settings!$B$6,"Qualified: nurture","Development pathway")))))
Y29: =IF($A29="","",IF(COUNTIF(F29:I29,"Yes")=4,"Pass","Fail")) | Z29: =IF($A29="","",IF(AND(IFERROR(MATCH(J29,Settings!$A$10:$A$14,0),0)>=MATCH(Settings!$B$4,Settings!$A$10:$A$14,0),K29="Yes",L29="Yes"),"Pass","Fail")) | AA29: =IF($A29="","",IF(COUNTIF(M29:P29,"Yes")=4,"Pass","Fail")) | AB29: =IF($A29="","",SUM(Q29:U29)) | AC29: =IF($A29="","",IF(OR(Y29="Fail",X29="Yes",V29<>"Yes"),"Not a fit",IF(OR(Z29="Fail",AA29="Fail"),"Development pathway",IF(AB29>=Settings!$B$5,"Qualified: high intent",IF(AB29>=Settings!$B$6,"Qualified: nurture","Development pathway")))))
Y30: =IF($A30="","",IF(COUNTIF(F30:I30,"Yes")=4,"Pass","Fail")) | Z30: =IF($A30="","",IF(AND(IFERROR(MATCH(J30,Settings!$A$10:$A$14,0),0)>=MATCH(Settings!$B$4,Settings!$A$10:$A$14,0),K30="Yes",L30="Yes"),"Pass","Fail")) | AA30: =IF($A30="","",IF(COUNTIF(M30:P30,"Yes")=4,"Pass","Fail")) | AB30: =IF($A30="","",SUM(Q30:U30)) | AC30: =IF($A30="","",IF(OR(Y30="Fail",X30="Yes",V30<>"Yes"),"Not a fit",IF(OR(Z30="Fail",AA30="Fail"),"Development pathway",IF(AB30>=Settings!$B$5,"Qualified: high intent",IF(AB30>=Settings!$B$6,"Qualified: nurture","Development pathway")))))
Y31: =IF($A31="","",IF(COUNTIF(F31:I31,"Yes")=4,"Pass","Fail")) | Z31: =IF($A31="","",IF(AND(IFERROR(MATCH(J31,Settings!$A$10:$A$14,0),0)>=MATCH(Settings!$B$4,Settings!$A$10:$A$14,0),K31="Yes",L31="Yes"),"Pass","Fail")) | AA31: =IF($A31="","",IF(COUNTIF(M31:P31,"Yes")=4,"Pass","Fail")) | AB31: =IF($A31="","",SUM(Q31:U31)) | AC31: =IF($A31="","",IF(OR(Y31="Fail",X31="Yes",V31<>"Yes"),"Not a fit",IF(OR(Z31="Fail",AA31="Fail"),"Development pathway",IF(AB31>=Settings!$B$5,"Qualified: high intent",IF(AB31>=Settings!$B$6,"Qualified: nurture","Development pathway")))))
Y32: =IF($A32="","",IF(COUNTIF(F32:I32,"Yes")=4,"Pass","Fail")) | Z32: =IF($A32="","",IF(AND(IFERROR(MATCH(J32,Settings!$A$10:$A$14,0),0)>=MATCH(Settings!$B$4,Settings!$A$10:$A$14,0),K32="Yes",L32="Yes"),"Pass","Fail")) | AA32: =IF($A32="","",IF(COUNTIF(M32:P32,"Yes")=4,"Pass","Fail")) | AB32: =IF($A32="","",SUM(Q32:U32)) | AC32: =IF($A32="","",IF(OR(Y32="Fail",X32="Yes",V32<>"Yes"),"Not a fit",IF(OR(Z32="Fail",AA32="Fail"),"Development pathway",IF(AB32>=Settings!$B$5,"Qualified: high intent",IF(AB32>=Settings!$B$6,"Qualified: nurture","Development pathway")))))
Y33: =IF($A33="","",IF(COUNTIF(F33:I33,"Yes")=4,"Pass","Fail")) | Z33: =IF($A33="","",IF(AND(IFERROR(MATCH(J33,Settings!$A$10:$A$14,0),0)>=MATCH(Settings!$B$4,Settings!$A$10:$A$14,0),K33="Yes",L33="Yes"),"Pass","Fail")) | AA33: =IF($A33="","",IF(COUNTIF(M33:P33,"Yes")=4,"Pass","Fail")) | AB33: =IF($A33="","",SUM(Q33:U33)) | AC33: =IF($A33="","",IF(OR(Y33="Fail",X33="Yes",V33<>"Yes"),"Not a fit",IF(OR(Z33="Fail",AA33="Fail"),"Development pathway",IF(AB33>=Settings!$B$5,"Qualified: high intent",IF(AB33>=Settings!$B$6,"Qualified: nurture","Development pathway")))))
Y34: =IF($A34="","",IF(COUNTIF(F34:I34,"Yes")=4,"Pass","Fail")) | Z34: =IF($A34="","",IF(AND(IFERROR(MATCH(J34,Settings!$A$10:$A$14,0),0)>=MATCH(Settings!$B$4,Settings!$A$10:$A$14,0),K34="Yes",L34="Yes"),"Pass","Fail")) | AA34: =IF($A34="","",IF(COUNTIF(M34:P34,"Yes")=4,"Pass","Fail")) | AB34: =IF($A34="","",SUM(Q34:U34)) | AC34: =IF($A34="","",IF(OR(Y34="Fail",X34="Yes",V34<>"Yes"),"Not a fit",IF(OR(Z34="Fail",AA34="Fail"),"Development pathway",IF(AB34>=Settings!$B$5,"Qualified: high intent",IF(AB34>=Settings!$B$6,"Qualified: nurture","Development pathway")))))
Y35: =IF($A35="","",IF(COUNTIF(F35:I35,"Yes")=4,"Pass","Fail")) | Z35: =IF($A35="","",IF(AND(IFERROR(MATCH(J35,Settings!$A$10:$A$14,0),0)>=MATCH(Settings!$B$4,Settings!$A$10:$A$14,0),K35="Yes",L35="Yes"),"Pass","Fail")) | AA35: =IF($A35="","",IF(COUNTIF(M35:P35,"Yes")=4,"Pass","Fail")) | AB35: =IF($A35="","",SUM(Q35:U35)) | AC35: =IF($A35="","",IF(OR(Y35="Fail",X35="Yes",V35<>"Yes"),"Not a fit",IF(OR(Z35="Fail",AA35="Fail"),"Development pathway",IF(AB35>=Settings!$B$5,"Qualified: high intent",IF(AB35>=Settings!$B$6,"Qualified: nurture","Development pathway")))))
Y36: =IF($A36="","",IF(COUNTIF(F36:I36,"Yes")=4,"Pass","Fail")) | Z36: =IF($A36="","",IF(AND(IFERROR(MATCH(J36,Settings!$A$10:$A$14,0),0)>=MATCH(Settings!$B$4,Settings!$A$10:$A$14,0),K36="Yes",L36="Yes"),"Pass","Fail")) | AA36: =IF($A36="","",IF(COUNTIF(M36:P36,"Yes")=4,"Pass","Fail")) | AB36: =IF($A36="","",SUM(Q36:U36)) | AC36: =IF($A36="","",IF(OR(Y36="Fail",X36="Yes",V36<>"Yes"),"Not a fit",IF(OR(Z36="Fail",AA36="Fail"),"Development pathway",IF(AB36>=Settings!$B$5,"Qualified: high intent",IF(AB36>=Settings!$B$6,"Qualified: nurture","Development pathway")))))
Y37: =IF($A37="","",IF(COUNTIF(F37:I37,"Yes")=4,"Pass","Fail")) | Z37: =IF($A37="","",IF(AND(IFERROR(MATCH(J37,Settings!$A$10:$A$14,0),0)>=MATCH(Settings!$B$4,Settings!$A$10:$A$14,0),K37="Yes",L37="Yes"),"Pass","Fail")) | AA37: =IF($A37="","",IF(COUNTIF(M37:P37,"Yes")=4,"Pass","Fail")) | AB37: =IF($A37="","",SUM(Q37:U37)) | AC37: =IF($A37="","",IF(OR(Y37="Fail",X37="Yes",V37<>"Yes"),"Not a fit",IF(OR(Z37="Fail",AA37="Fail"),"Development pathway",IF(AB37>=Settings!$B$5,"Qualified: high intent",IF(AB37>=Settings!$B$6,"Qualified: nurture","Development pathway")))))
Y38: =IF($A38="","",IF(COUNTIF(F38:I38,"Yes")=4,"Pass","Fail")) | Z38: =IF($A38="","",IF(AND(IFERROR(MATCH(J38,Settings!$A$10:$A$14,0),0)>=MATCH(Settings!$B$4,Settings!$A$10:$A$14,0),K38="Yes",L38="Yes"),"Pass","Fail")) | AA38: =IF($A38="","",IF(COUNTIF(M38:P38,"Yes")=4,"Pass","Fail")) | AB38: =IF($A38="","",SUM(Q38:U38)) | AC38: =IF($A38="","",IF(OR(Y38="Fail",X38="Yes",V38<>"Yes"),"Not a fit",IF(OR(Z38="Fail",AA38="Fail"),"Development pathway",IF(AB38>=Settings!$B$5,"Qualified: high intent",IF(AB38>=Settings!$B$6,"Qualified: nurture","Development pathway")))))
... Y221: =IF($A221="","",IF(COUNTIF(F221:I221,"Yes")=4,"Pass","Fail")) | Z221: =IF($A221="","",IF(AND(IFERROR(MATCH(J221,Settings!$A$10:$A$14,0),0)>=MATCH(Settings!$B$4,Settings!$A$10:$A$14,0),K221="Yes",L221="Yes"),"Pass","Fail")) | AA221: =IF($A221="","",IF(COUNTIF(M221:P221,"Yes")=4,"Pass","Fail")) | AB221: =IF($A221="","",SUM(Q221:U221)) | AC221: =IF($A221="","",IF(OR(Y221="Fail",X221="Yes",V221<>"Yes"),"Not a fit",IF(OR(Z221="Fail",AA221="Fail"),"Development pathway",IF(AB221>=Settings!$B$5,"Qualified: high intent",IF(AB221>=Settings!$B$6,"Qualified: nurture","Development pathway")))))

Sheet Question Bank
A1: Question Bank
A3: # | B3: Ask | C3: Strong answer / 2 points | D3: Red flag / 0 points | E3: Record in Backend as
A4: A. Is it a real business? (gate)
A5: A1 | B5: What is the registered name of the business, and who owns it? | C5: Legal name matches the register. Owner named clearly. | D5: Name does not match. Ownership vague. | E5: Yes if strong
A6: A2 | B6: How long have you been trading, and how many paying customers in the last 12 months? | C6: Specific start date and number. | D6: No number offered. | E6: Yes if strong
A7: A3 | B7: Tell me about your last three customers. What did they buy and how did they pay? | C7: Recent, specific, invoice or card. | D7: Only friends or family. | E7: Yes if strong
A8: A4 | B8: Where can I see the business in public? | C8: Website, reviews, address, trading history. | D8: A recent social profile only. | E8: Yes if strong
A9: B. Does it have turnover? (gate)
A10: B1 | B10: Which band was your turnover in the last full 12 months? | C10: Answers without hesitation. | D10: Declines, or conflicts with public records. | E10: Select band
A11: B2 | B11: Roughly what share comes from repeat customers? | C11: Knows the split. | D11: No idea. | E11: Yes if strong
A12: B3 | B12: Who prepares your accounts, and are filings up to date? | C12: Named accountant. Filings current. | D12: Overdue filings. | E12: Yes if strong
A13: C. Leadership beyond the founder? (gate)
A14: C1 | B14: Apart from you, who makes decisions in the business? | C14: Names another person with real authority. | D14: “It is all me.” | E14: Yes if strong
A15: C2 | B15: If you were away for two weeks, who would run it? | C15: Named person and routines. | D15: The business would stop. | E15: Yes if strong
A16: C3 | B16: Who owns sales, delivery and finance? | C16: Named owner for each. | D16: Founder owns all three. | E16: Yes if strong
A17: C4 | B17: How often does leadership meet, and what did you decide last time? | C17: Regular rhythm. Recalls a decision. | D17: No rhythm. | E17: Yes if strong
A18: D. Intent to grow (scored)
A19: D1 | B19: Where do you want the business in 12 months, in numbers? | C19: Specific target. | D19: “Just to grow.” | E19: 0, 1 or 2
A20: D2 | B20: What have you invested in growth in the last six months? | C20: Named spend, hire or system. | D20: Nothing. | E20: 0, 1 or 2
A21: D3 | B21: What is stopping you getting there today? | C21: Specific, owned constraint. | D21: Blames the market. | E21: 0, 1 or 2
A22: D4 | B22: What happens if nothing changes in 12 months? | C22: Clear cost. | D22: “We would be fine.” | E22: 0, 1 or 2
A23: D5 | B23: If we found the right support, when would you start, and who else must agree? | C23: Within 30 days. Decision maker named. | D23: No timeframe. | E23: 0, 1 or 2
A24: E. Kingdom alignment
A25: E1 | B25: Are you a Christian-led business? Who holds that leadership, and what is their role? | C25: A named Christian owner or leader with real authority over direction. | D25: Unclear who leads, or faith has no bearing on leadership. | E25: Yes or No (gate)
A26: E2 | B26: Are you mindful to meet and add value to other Christian businesses? Give a recent example. | C26: 2: A recent, concrete example. 1: Willing, no example yet. | D26: 0: Not a priority. | E26: 0, 1 or 2
A28: Cross-checks: customers (A2) against turnover (B1); leaders named (C1, C3) against the public register; growth target (D1) against investment (D2). Record Yes in the Backend if any concern is unresolved.

Sheet Settings
A1: Settings
A2: Yellow cells are yours to change. Everything else updates automatically.
A4: Minimum turnover band | B4: Under £50k | C4: Set by City on a Hill. Left at the lowest band so no business is excluded until you choose a minimum.
A5: High intent score (out of 10) | B5: 8 | C5: From the Growth Partner Qualification guide.
A6: Nurture score (out of 10) | B6: 5 | C6: From the Growth Partner Qualification guide.
A9: Turnover bands (lowest to highest)
A10: Under £50k | B10: 1
A11: £50k to £250k | B11: 2
A12: £250k to £1m | B12: 3
A13: £1m to £5m | B13: 4
A14: Over £5m | B14: 5
